odoo/addons/stock_picking_line_sequence/README.rst
odoo/addons/stock_picking_line_sequence/__init__.py
odoo/addons/stock_picking_line_sequence/__manifest__.py
odoo/addons/stock_picking_line_sequence/init_hooks.py
odoo/addons/stock_picking_line_sequence/i18n/ca.po
odoo/addons/stock_picking_line_sequence/i18n/de.po
odoo/addons/stock_picking_line_sequence/i18n/es.po
odoo/addons/stock_picking_line_sequence/i18n/es_MX.po
odoo/addons/stock_picking_line_sequence/i18n/fi.po
odoo/addons/stock_picking_line_sequence/i18n/fr.po
odoo/addons/stock_picking_line_sequence/i18n/hr.po
odoo/addons/stock_picking_line_sequence/i18n/it.po
odoo/addons/stock_picking_line_sequence/i18n/nl_NL.po
odoo/addons/stock_picking_line_sequence/i18n/pt.po
odoo/addons/stock_picking_line_sequence/i18n/pt_BR.po
odoo/addons/stock_picking_line_sequence/i18n/sl.po
odoo/addons/stock_picking_line_sequence/i18n/stock_picking_line_sequence.pot
odoo/addons/stock_picking_line_sequence/i18n/tr.po
odoo/addons/stock_picking_line_sequence/i18n/tr_TR.po
odoo/addons/stock_picking_line_sequence/migrations/18.0.1.0.0/pre-migration.py
odoo/addons/stock_picking_line_sequence/models/__init__.py
odoo/addons/stock_picking_line_sequence/models/stock_move.py
odoo/addons/stock_picking_line_sequence/models/stock_move_line.py
odoo/addons/stock_picking_line_sequence/models/stock_picking.py
odoo/addons/stock_picking_line_sequence/readme/CONTRIBUTORS.md
odoo/addons/stock_picking_line_sequence/readme/DESCRIPTION.md
odoo/addons/stock_picking_line_sequence/readme/USAGE.md
odoo/addons/stock_picking_line_sequence/report/report_deliveryslip.xml
odoo/addons/stock_picking_line_sequence/static/description/icon.png
odoo/addons/stock_picking_line_sequence/static/description/index.html
odoo/addons/stock_picking_line_sequence/tests/__init__.py
odoo/addons/stock_picking_line_sequence/tests/test_move_lines_sequence.py
odoo/addons/stock_picking_line_sequence/views/stock_picking_views.xml
odoo_addon_stock_picking_line_sequence-18.0.1.0.1.1.dist-info/METADATA
odoo_addon_stock_picking_line_sequence-18.0.1.0.1.1.dist-info/WHEEL
odoo_addon_stock_picking_line_sequence-18.0.1.0.1.1.dist-info/top_level.txt
odoo_addon_stock_picking_line_sequence-18.0.1.0.1.1.dist-info/RECORD
