Metadata-Version: 2.1
Name: odoo-addon-stock_picking_line_sequence
Version: 18.0.1.0.1.1
Requires-Python: >=3.10
Requires-Dist: odoo==18.0.*
Summary: Manages the order of stock moves by displaying its sequence
Home-page: https://github.com/OCA/stock-logistics-workflow
License: AGPL-3
Author: Camptocamp, ForgeFlow, Serpent CS, Odoo Community Association (OCA), ArcheTI
Author-email: support@odoo-community.org
Classifier: Programming Language :: Python
Classifier: Framework :: Odoo
Classifier: Framework :: Odoo :: 18.0
Classifier: License :: OSI Approved :: GNU Affero General Public License v3
